{
  "spdxVersion": "SPDX-2.3",
  "dataLicense": "CC0-1.0",
  "SPDXID": "SPDXRef-DOCUMENT",
  "name": "SBOM-20250703-205828",
  "documentNamespace": "https://sbom-platform.local/SBOM-20250703-205828",
  "creationInfo": {
    "created": "2025-07-03T20:58:28.873167Z",
    "creators": [
      "Tool: SBOM Generation Platform-1.0.0"
    ]
  },
  "packages": [
    {
      "SPDXID": "SPDXRef-Package-0",
      "name": "commons-lang3",
      "version": "3.12.0",
      "downloadLocation": "/pom.xml",
      "filesAnalyzed": false,
      "copyrightText": "NOASSERTION",
      "licenseConcluded": "NOASSERTION",
      "externalRefs": [
        {
          "referenceCategory": "PACKAGE_MANAGER",
          "referenceType": "purl",
          "referenceLocator": "pkg:maven/commons-lang3@3.12.0"
        }
      ],
      "supplier": "Tool: syft"
    },
    {
      "SPDXID": "SPDXRef-Package-1",
      "name": "jackson-databind",
      "version": "2.15.2",
      "downloadLocation": "/pom.xml",
      "filesAnalyzed": false,
      "copyrightText": "NOASSERTION",
      "licenseConcluded": "NOASSERTION",
      "externalRefs": [
        {
          "referenceCategory": "PACKAGE_MANAGER",
          "referenceType": "purl",
          "referenceLocator": "pkg:maven/jackson-databind@2.15.2"
        }
      ],
      "supplier": "Tool: syft"
    },
    {
      "SPDXID": "SPDXRef-Package-2",
      "name": "junit",
      "version": "4.13.2",
      "downloadLocation": "/pom.xml",
      "filesAnalyzed": false,
      "copyrightText": "NOASSERTION",
      "licenseConcluded": "NOASSERTION",
      "externalRefs": [
        {
          "referenceCategory": "PACKAGE_MANAGER",
          "referenceType": "purl",
          "referenceLocator": "pkg:maven/junit@4.13.2"
        }
      ],
      "supplier": "Tool: syft"
    },
    {
      "SPDXID": "SPDXRef-Package-3",
      "name": "spring-boot-starter-web",
      "version": "3.1.0",
      "downloadLocation": "/pom.xml",
      "filesAnalyzed": false,
      "copyrightText": "NOASSERTION",
      "licenseConcluded": "NOASSERTION",
      "externalRefs": [
        {
          "referenceCategory": "PACKAGE_MANAGER",
          "referenceType": "purl",
          "referenceLocator": "pkg:maven/spring-boot-starter-web@3.1.0"
        }
      ],
      "supplier": "Tool: syft"
    },
    {
      "SPDXID": "SPDXRef-Package-4",
      "name": "test-app",
      "version": "1.0.0",
      "downloadLocation": "/pom.xml",
      "filesAnalyzed": false,
      "copyrightText": "NOASSERTION",
      "licenseConcluded": "NOASSERTION",
      "externalRefs": [
        {
          "referenceCategory": "PACKAGE_MANAGER",
          "referenceType": "purl",
          "referenceLocator": "pkg:maven/test-app@1.0.0"
        }
      ],
      "supplier": "Tool: syft"
    },
    {
      "SPDXID": "SPDXRef-Package-5",
      "name": "boost",
      "version": "1.82.0",
      "downloadLocation": "/conanfile.txt",
      "filesAnalyzed": false,
      "copyrightText": "NOASSERTION",
      "licenseConcluded": "NOASSERTION",
      "externalRefs": [
        {
          "referenceCategory": "PACKAGE_MANAGER",
          "referenceType": "purl",
          "referenceLocator": "pkg:conan/boost@1.82.0"
        }
      ],
      "supplier": "Tool: syft"
    },
    {
      "SPDXID": "SPDXRef-Package-6",
      "name": "fmt",
      "version": "10.1.1",
      "downloadLocation": "/conanfile.txt",
      "filesAnalyzed": false,
      "copyrightText": "NOASSERTION",
      "licenseConcluded": "NOASSERTION",
      "externalRefs": [
        {
          "referenceCategory": "PACKAGE_MANAGER",
          "referenceType": "purl",
          "referenceLocator": "pkg:conan/fmt@10.1.1"
        }
      ],
      "supplier": "Tool: syft"
    },
    {
      "SPDXID": "SPDXRef-Package-7",
      "name": "libcurl",
      "version": "8.2.1",
      "downloadLocation": "/conanfile.txt",
      "filesAnalyzed": false,
      "copyrightText": "NOASSERTION",
      "licenseConcluded": "NOASSERTION",
      "externalRefs": [
        {
          "referenceCategory": "PACKAGE_MANAGER",
          "referenceType": "purl",
          "referenceLocator": "pkg:conan/libcurl@8.2.1"
        }
      ],
      "supplier": "Tool: syft"
    },
    {
      "SPDXID": "SPDXRef-Package-8",
      "name": "openssl",
      "version": "1.1.1u",
      "downloadLocation": "/conanfile.txt",
      "filesAnalyzed": false,
      "copyrightText": "NOASSERTION",
      "licenseConcluded": "NOASSERTION",
      "externalRefs": [
        {
          "referenceCategory": "PACKAGE_MANAGER",
          "referenceType": "purl",
          "referenceLocator": "pkg:conan/openssl@1.1.1u"
        }
      ],
      "supplier": "Tool: syft"
    },
    {
      "SPDXID": "SPDXRef-Package-9",
      "name": "spdlog",
      "version": "1.12.0",
      "downloadLocation": "/conanfile.txt",
      "filesAnalyzed": false,
      "copyrightText": "NOASSERTION",
      "licenseConcluded": "NOASSERTION",
      "externalRefs": [
        {
          "referenceCategory": "PACKAGE_MANAGER",
          "referenceType": "purl",
          "referenceLocator": "pkg:conan/spdlog@1.12.0"
        }
      ],
      "supplier": "Tool: syft"
    },
    {
      "SPDXID": "SPDXRef-Package-10",
      "name": "sqlite3",
      "version": "3.42.0",
      "downloadLocation": "/conanfile.txt",
      "filesAnalyzed": false,
      "copyrightText": "NOASSERTION",
      "licenseConcluded": "NOASSERTION",
      "externalRefs": [
        {
          "referenceCategory": "PACKAGE_MANAGER",
          "referenceType": "purl",
          "referenceLocator": "pkg:conan/sqlite3@3.42.0"
        }
      ],
      "supplier": "Tool: syft"
    },
    {
      "SPDXID": "SPDXRef-Package-11",
      "name": "zlib",
      "version": "1.2.13",
      "downloadLocation": "/conanfile.txt",
      "filesAnalyzed": false,
      "copyrightText": "NOASSERTION",
      "licenseConcluded": "NOASSERTION",
      "externalRefs": [
        {
          "referenceCategory": "PACKAGE_MANAGER",
          "referenceType": "purl",
          "referenceLocator": "pkg:conan/zlib@1.2.13"
        }
      ],
      "supplier": "Tool: syft"
    }
  ]
}